Metadata-Version: 2.1
Name: gmsh-sdk
Version: 4.5.6.post1
Summary: Gmsh SDK installer. Gmsh is a three-dimensional finite element mesh generator.
Home-page: https://github.com/mrkwjc/gmsh-sdk
Maintainer: Marek Wojciechowski
Maintainer-email: mrkwjc@gmail.com
License: GPL-2
Keywords: fem,mesh,finite element method
Platform: Posix
Platform: Windows
Classifier: Development Status :: 5 - Production/Stable
Classifier: Intended Audience :: Education
Classifier: Intended Audience :: Science/Research
Classifier: License :: OSI Approved :: GNU General Public License v2 or later (GPLv2+)
Classifier: Operating System :: POSIX :: Linux
Classifier: Operating System :: Microsoft :: Windows
Classifier: Operating System :: MacOS :: MacOS X
Classifier: Programming Language :: C
Classifier: Programming Language :: C++
Classifier: Programming Language :: Python :: Implementation :: CPython
Classifier: Topic :: Scientific/Engineering
